pypi_upload.sh
release-egg.sh
setup.cfg
setup.py
docbook2sla/CHANGES.txt
docbook2sla/LICENSE.txt
docbook2sla/README.txt
docbook2sla/__init__.py
docbook2sla/docbook2sla.py
docbook2sla/interfaces.py
docbook2sla/logger.py
docbook2sla/test.py
docbook2sla/util.py
docbook2sla/version.txt
docbook2sla.egg-info/PKG-INFO
docbook2sla.egg-info/SOURCES.txt
docbook2sla.egg-info/dependency_links.txt
docbook2sla.egg-info/entry_points.txt
docbook2sla.egg-info/not-zip-safe
docbook2sla.egg-info/paster_plugins.txt
docbook2sla.egg-info/requires.txt
docbook2sla.egg-info/top_level.txt
docbook2sla/output/output.sla
docbook2sla/schema/document.xsd
docbook2sla/schema/object.xsd
docbook2sla/schema/scribus.xsd
docbook2sla/tests/__init__.py
docbook2sla/tests/alltests.py
docbook2sla/tests/test_create.py
docbook2sla/tests/test_docbook2pageobject.py
docbook2sla/tests/test_image.py
docbook2sla/tests/test_syncronize.py
docbook2sla/tests/test_transformation.py
docbook2sla/tests/test_wrapper.py
docbook2sla/tests/data/__init__.py
docbook2sla/tests/data/docbook1.xml
docbook2sla/tests/data/expected_result.sla
docbook2sla/tests/data/merge.xsl
docbook2sla/tests/data/merge_complex_pageobjects.xsl
docbook2sla/tests/data/scribus1.sla
docbook2sla/tests/data/test1.html
docbook2sla/tests/data/test2.html
docbook2sla/tests/data/testDocBook2Pageobjects.input.xml
docbook2sla/tests/data/testDocBook2Pageobjects.output.expected.xml
docbook2sla/tests/data/test_wrapper_expected.xml
docbook2sla/tests/data/test_wrapper_input.xml
docbook2sla/tests/data/test_wrapper_secondinput.xml
docbook2sla/tests/data/output/create_output.sla
docbook2sla/tests/data/output/pageobjects.xml
docbook2sla/tests/data/output/syncronize_output.sla
docbook2sla/tests/data/scribus/clean134.sla
docbook2sla/tests/data/test_docbook2sla/testTransformation.expected.xml
docbook2sla/tests/data/test_docbook2sla/testTransformation.input.xml
docbook2sla/tests/data/test_docbook2sla/testTransformation.xsl
docbook2sla/tests/data/test_docbook2sla/testTransformationWithParam.expected.xml
docbook2sla/tests/data/test_docbook2sla/testTransformationWithParam.input.xml
docbook2sla/tests/data/test_docbook2sla/testTransformationWithParam.secondinput.xml
docbook2sla/tests/data/test_docbook2sla/testTransformationWithParam.xsl
