Metadata-Version: 1.0
Name: docbook2sla
Version: 0.0.16
Summary: A Python interface to convert DocBook to Scribus
Home-page: http://scribus.zmag.de
Author: Timo Stollenwerk
Author-email: timo@zmag.de
License: GPL
Keywords: docbook scribus converter dtp
Platform: UNKNOWN
Classifier: License :: OSI Approved :: GNU General Public License (GPL)
Classifier: Programming Language :: Python
Classifier: Development Status :: 2 - Pre-Alpha
Classifier: Intended Audience :: Developers
Classifier: Topic :: Internet
Classifier: Topic :: Multimedia :: Graphics :: Editors
